format.py
lint.py
script.py
utils.py
lhy_formatter_linter-0.0.10.dist-info/LICENSE.md
lhy_formatter_linter-0.0.10.dist-info/METADATA
lhy_formatter_linter-0.0.10.dist-info/WHEEL
lhy_formatter_linter-0.0.10.dist-info/entry_points.txt
lhy_formatter_linter-0.0.10.dist-info/top_level.txt
lhy_formatter_linter-0.0.10.dist-info/RECORD
