Metadata-Version: 2.2
Name: lhy-formatter-linter
Version: 0.0.10
Summary: This package provides formatters and linters for CMake, C++, and Python, making it ideal for developers who work with both C++ and Python.
Author-email: Yuan SUN <sunyuan860510@gmail.com>
Maintainer-email: Yuan SUN <sunyuan860510@gmail.com>
License: MIT License
Project-URL: Homepage, https://github.com/sygslhy/lhy-formatter-linter
Project-URL: Repository, https://github.com/sygslhy/lhy-formatter-linter
Project-URL: Issues, https://github.com/sygslhy/lhy-formatter-linter/issues
Project-URL: Releases, https://github.com/sygslhy/lhy-formatter-linter/releases
Keywords: cmake-format,lint,clang-format,clang-tidy,flake8,code format,code lint,lhy
Classifier: Development Status :: 4 - Beta
Classifier: Programming Language :: Python :: 3
Classifier: Programming Language :: Python :: 3 :: Only
Classifier: License :: OSI Approved :: MIT License
Classifier: Operating System :: OS Independent
Classifier: Topic :: Software Development
Classifier: Intended Audience :: Developers
Requires-Python: >=3.9
License-File: LICENSE.md
Requires-Dist: cmake-format>=0.6.13
Requires-Dist: clang-format>=13.0.1
Requires-Dist: clang-tidy>=13.0.1.1
Requires-Dist: yapf>=0.43.0
Requires-Dist: flake8>=7.1.1
Requires-Dist: isort>=6.0.0
